polars_profiling/__init__.py
zarque_profiling/__init__.py
zarque_profiling/compare_reports.py
zarque_profiling/config.py
zarque_profiling/config_default.yaml
zarque_profiling/config_minimal.yaml
zarque_profiling/expectations_report.py
zarque_profiling/profile_report.py
zarque_profiling/serialize_report.py
zarque_profiling/version.py
zarque_profiling/controller/__init__.py
zarque_profiling/controller/console.py
zarque_profiling/controller/pandas_decorator.py
zarque_profiling/model/__init__.py
zarque_profiling/model/alerts.py
zarque_profiling/model/correlations.py
zarque_profiling/model/dataframe.py
zarque_profiling/model/describe.py
zarque_profiling/model/duplicates.py
zarque_profiling/model/expectation_algorithms.py
zarque_profiling/model/handler.py
zarque_profiling/model/missing.py
zarque_profiling/model/pairwise.py
zarque_profiling/model/sample.py
zarque_profiling/model/summarizer.py
zarque_profiling/model/summary.py
zarque_profiling/model/summary_algorithms.py
zarque_profiling/model/table.py
zarque_profiling/model/typeset.py
zarque_profiling/model/typeset_relations.py
zarque_profiling/model/pandas/__init__.py
zarque_profiling/model/pandas/correlations_pandas.py
zarque_profiling/model/pandas/dataframe_pandas.py
zarque_profiling/model/pandas/describe_boolean_pandas.py
zarque_profiling/model/pandas/describe_categorical_pandas.py
zarque_profiling/model/pandas/describe_counts_pandas.py
zarque_profiling/model/pandas/describe_date_pandas.py
zarque_profiling/model/pandas/describe_file_pandas.py
zarque_profiling/model/pandas/describe_generic_pandas.py
zarque_profiling/model/pandas/describe_image_pandas.py
zarque_profiling/model/pandas/describe_numeric_pandas.py
zarque_profiling/model/pandas/describe_path_pandas.py
zarque_profiling/model/pandas/describe_supported_pandas.py
zarque_profiling/model/pandas/describe_timeseries_pandas.py
zarque_profiling/model/pandas/describe_url_pandas.py
zarque_profiling/model/pandas/discretize_pandas.py
zarque_profiling-0.5.17.dist-info/licenses/LICENSE
zarque_profiling-0.5.17.dist-info/METADATA
zarque_profiling-0.5.17.dist-info/WHEEL
zarque_profiling-0.5.17.dist-info/entry_points.txt
zarque_profiling-0.5.17.dist-info/top_level.txt
zarque_profiling-0.5.17.dist-info/RECORD
