Metadata-Version: 2.4
Name: zarque-profiling
Version: 0.5.17
Summary: Data profiling tools for Big Data
Home-page: https://github.com/crescendo-medix/zarque-profiling
Author: Crescendo Medix
Author-email: g-ikeba@nifty.com
License: MIT
Keywords: big-data polars pandas data-profiling eda data-science data-analysis python jupyter ipython
Classifier: Development Status :: 5 - Production/Stable
Classifier: Topic :: Scientific/Engineering :: Information Analysis
Classifier: License :: OSI Approved :: MIT License
Classifier: Framework :: IPython
Classifier: Programming Language :: Python :: 3
Classifier: Programming Language :: Python :: 3.7
Classifier: Programming Language :: Python :: 3.8
Classifier: Programming Language :: Python :: 3.9
Classifier: Programming Language :: Python :: 3.10
Requires-Python: >=3.7, <3.12
License-File: LICENSE
Requires-Dist: scipy<1.13,>=1.4.1
Requires-Dist: pandas<2.3,>1.1
Requires-Dist: matplotlib<3.9,>=3.7
Requires-Dist: pydantic<2.7,>=1.8.1
Requires-Dist: PyYAML<6.1,>=5.0.0
Requires-Dist: jinja2<3.2,>=2.11.1
Requires-Dist: visions[type_image_path]>=0.8.1
Requires-Dist: numpy>=1.21
Requires-Dist: polars>=1.24.0
Requires-Dist: htmlmin==0.1.12
Requires-Dist: phik<0.13,>=0.11.1
Requires-Dist: requests<2.32,>=2.24.0
Requires-Dist: tqdm<4.67,>=4.65
Requires-Dist: seaborn<0.14,>=0.10.1
Requires-Dist: multimethod>=2.0
Requires-Dist: statsmodels<0.15,>=0.13.2
Requires-Dist: typeguard<4.3,>=2.13.2
Provides-Extra: notebook
Requires-Dist: jupyter-client>=5.3.4; extra == "notebook"
Requires-Dist: jupyter-core>=4.6.3; extra == "notebook"
Requires-Dist: ipywidgets>=7.5.1; extra == "notebook"
Provides-Extra: unicode
Requires-Dist: tangled-up-in-unicode==0.2.0; extra == "unicode"
Dynamic: author
Dynamic: author-email
Dynamic: classifier
Dynamic: description
Dynamic: description-content-type
Dynamic: home-page
Dynamic: keywords
Dynamic: license
Dynamic: license-file
Dynamic: provides-extra
Dynamic: requires-dist
Dynamic: requires-python
Dynamic: summary
